tunits_core.cpython-313-darwin.so
tunits/units.py
tunits/units_with_dimension.py
tunits/__init__.py
tunits/py.typed
tunits/core/__init__.pyi
tunits/core/_all_cythonized.c
tunits/core/__init__.py
tunits/core/_all_cythonized.pyx
tunits/core/py.typed
tunits/core/cython/conversion.pyx
tunits/core/cython/base_unit_data.pyx
tunits/core/cython/prefix_data.pyx
tunits/core/cython/unit_grammar.pyx
tunits/core/cython/with_unit_value_array.pyx
tunits/core/cython/unit.pyx
tunits/core/cython/dimension.pyx
tunits/core/cython/unit_database.pyx
tunits/core/cython/frac.pyx
tunits/core/cython/proto.pyx
tunits/core/cython/unit_array.pyx
tunits/core/cython/physical_constant_data.pyx
tunits/core/cython/derived_unit_data.pyx
tunits/core/cython/with_unit_value.pyx
tunits/core/cython/unit_mismatch_error.pyx
tunits/core/cython/with_unit.pyx
tunits/proto/tunits.proto
tunits/proto/tunits_pb2.pyi
tunits/proto/tunits_pb2.py
typedunits-0.0.1.dist-info/RECORD
typedunits-0.0.1.dist-info/WHEEL
typedunits-0.0.1.dist-info/top_level.txt
typedunits-0.0.1.dist-info/METADATA
typedunits-0.0.1.dist-info/licenses/LICENSE
typedunits-0.0.1.dist-info/licenses/AUTHORS
