Metadata-Version: 2.4
Name: typedunits
Version: 0.0.1
Summary: A fast units and dimensions library with support for static dimensionality checking and protobuffer serialization.
Home-page: https://github.com/quantumlib/TypedUnits
Author: The TUnits Authors
License: Apache 2
Requires-Python: >=3.10.0
License-File: LICENSE
License-File: AUTHORS
Requires-Dist: attrs
Requires-Dist: cython>=3.0.0
Requires-Dist: numpy>=1.23.0
Requires-Dist: protobuf>=4.25
Requires-Dist: pyparsing
Dynamic: author
Dynamic: description
Dynamic: description-content-type
Dynamic: home-page
Dynamic: license
Dynamic: license-file
Dynamic: requires-dist
Dynamic: requires-python
Dynamic: summary
